MANIFEST.in
README.rst
classless.py
setup.py
Classless.egg-info/PKG-INFO
Classless.egg-info/SOURCES.txt
Classless.egg-info/dependency_links.txt
Classless.egg-info/top_level.txt