Metadata-Version: 1.1
Name: Classless
Version: 0.0.2
Summary: Easily curry multiple functions to a given list of arguments without using classes
Home-page: https://github.com/djyale/classless
Author: David J Gordon
Author-email: djyale@gmail.com
License: BSD
Keywords: class meta
Platform: UNKNOWN
Classifier: Development Status :: 3 - Alpha
Classifier: Programming Language :: Python
Classifier: Programming Language :: Python :: 2.7
Classifier: Topic :: Utilities
Classifier: Operating System :: OS Independent
Classifier: Natural Language :: English
Classifier: License :: OSI Approved :: BSD License
